easy_download.py
easy_download_setup-1.0.0.dist-info/METADATA
easy_download_setup-1.0.0.dist-info/WHEEL
easy_download_setup-1.0.0.dist-info/top_level.txt
easy_download_setup-1.0.0.dist-info/RECORD
